retile.py
retile-0.2.1.dist-info/LICENSE.txt
retile-0.2.1.dist-info/METADATA
retile-0.2.1.dist-info/WHEEL
retile-0.2.1.dist-info/entry_points.txt
retile-0.2.1.dist-info/top_level.txt
retile-0.2.1.dist-info/RECORD
