Metadata-Version: 2.1
Name: retile
Version: 0.2.1
Author-email: Karl Knechtel <zahlman@proton.me>
License: MIT License
Classifier: Development Status :: 1 - Planning
Classifier: Programming Language :: Python :: 3
License-File: LICENSE.txt
Requires-Dist: imageio
